INSTALL.md
LICENSE
MANIFEST.in
README.rst
setup.py
qiita_core/__init__.py
qiita_core/configuration_manager.py
qiita_core/environment_manager.py
qiita_core/exceptions.py
qiita_core/qiita_settings.py
qiita_core/util.py
qiita_core/support_files/config_test.cfg
qiita_db/__init__.py
qiita_db/analysis.py
qiita_db/base.py
qiita_db/commands.py
qiita_db/data.py
qiita_db/environment_manager.py
qiita_db/exceptions.py
qiita_db/investigation.py
qiita_db/job.py
qiita_db/logger.py
qiita_db/meta_util.py
qiita_db/ontology.py
qiita_db/parameters.py
qiita_db/portal.py
qiita_db/reference.py
qiita_db/search.py
qiita_db/sql_connection.py
qiita_db/study.py
qiita_db/user.py
qiita_db/util.py
qiita_db/metadata_template/__init__.py
qiita_db/metadata_template/base_metadata_template.py
qiita_db/metadata_template/constants.py
qiita_db/metadata_template/prep_template.py
qiita_db/metadata_template/sample_template.py
qiita_db/metadata_template/util.py
qiita_db/metadata_template/test/__init__.py
qiita_db/metadata_template/test/test_base_metadata_template.py
qiita_db/metadata_template/test/test_prep_template.py
qiita_db/metadata_template/test/test_sample_template.py
qiita_db/metadata_template/test/test_util.py
qiita_db/support_files/populate_test_db.sql
qiita_db/support_files/qiita-db-settings.sql
qiita_db/support_files/qiita-db-unpatched.dbs
qiita_db/support_files/qiita-db-unpatched.sql
qiita_db/support_files/qiita-db.dbs
qiita_db/support_files/qiita-db.html
qiita_db/support_files/parameter_files/default_sortmerna_params.txt
qiita_db/support_files/patches/.gitignore
qiita_db/support_files/patches/0.sql
qiita_db/support_files/patches/1.sql
qiita_db/support_files/patches/10.sql
qiita_db/support_files/patches/11.sql
qiita_db/support_files/patches/12.sql
qiita_db/support_files/patches/13.sql
qiita_db/support_files/patches/14.sql
qiita_db/support_files/patches/15.sql
qiita_db/support_files/patches/16.sql
qiita_db/support_files/patches/17.sql
qiita_db/support_files/patches/18.sql
qiita_spots.egg-info/PKG-INFO
qiita_spots.egg-info/SOURCES.txt
qiita_spots.egg-info/dependency_links.txt
qiita_spots.egg-info/requires.txt
qiita_spots.egg-info/top_level.txt
